sacada/SACADA.py
sacada/__init__.py
sacada_python-0.0.7.data/scripts/sacada
sacada_python-0.0.7.dist-info/LICENSE
sacada_python-0.0.7.dist-info/METADATA
sacada_python-0.0.7.dist-info/WHEEL
sacada_python-0.0.7.dist-info/top_level.txt
sacada_python-0.0.7.dist-info/RECORD
