Metadata-Version: 2.1
Name: sacada-python
Version: 0.0.7
Summary: Python API for the SACADA data acquisition system
Home-page: https://git.cta.if.ufrgs.br/SACADA/sacada-python
Author: Pedro Henrique Capp Kopper
Author-email: pedro.kopper@ufrgs.br
License: UNKNOWN
Platform: UNKNOWN
Classifier: Programming Language :: Python :: 3
Classifier: Development Status :: 3 - Alpha
Classifier: License :: OSI Approved :: GNU General Public License v3 (GPLv3)
Classifier: Natural Language :: Portuguese (Brazilian)
Classifier: Topic :: Scientific/Engineering
Classifier: Operating System :: OS Independent
Requires-Python: >=3.5
Requires-Dist: pyserial
Requires-Dist: tqdm
Requires-Dist: click
Requires-Dist: thermocouples-reference
Requires-Dist: scipy
